touch_calibrator.cpython-36m-x86_64-linux-gnu.so
touch_calibrator-1.20210526.dist-info/METADATA
touch_calibrator-1.20210526.dist-info/WHEEL
touch_calibrator-1.20210526.dist-info/entry_points.txt
touch_calibrator-1.20210526.dist-info/top_level.txt
touch_calibrator-1.20210526.dist-info/RECORD
