Metadata-Version: 2.1
Name: touch-calibrator
Version: 1.20210526
Summary: UNKNOWN
Home-page: UNKNOWN
Author-email: sa@eri.su
License: UNKNOWN
Platform: UNKNOWN
Requires-Python: >=3.5
Requires-Dist: PyGObject
